pyquearcode/__init__.py
pyquearcode/logo.png
pyquearcode/locales/ar/LC_MESSAGES/quearcode.mo
pyquearcode/locales/bn/LC_MESSAGES/quearcode.mo
pyquearcode/locales/de/LC_MESSAGES/quearcode.mo
pyquearcode/locales/en/LC_MESSAGES/quearcode.mo
pyquearcode/locales/es/LC_MESSAGES/quearcode.mo
pyquearcode/locales/hi/LC_MESSAGES/quearcode.mo
pyquearcode/locales/ja/LC_MESSAGES/quearcode.mo
pyquearcode/locales/ko/LC_MESSAGES/quearcode.mo
pyquearcode/locales/pt/LC_MESSAGES/quearcode.mo
pyquearcode/locales/uk/LC_MESSAGES/quearcode.mo
pyquearcode/locales/zh/LC_MESSAGES/quearcode.mo
quearcode-0.4.2.data/scripts/quearcode
quearcode-0.4.2.dist-info/licenses/COPYING
quearcode-0.4.2.dist-info/METADATA
quearcode-0.4.2.dist-info/WHEEL
quearcode-0.4.2.dist-info/top_level.txt
quearcode-0.4.2.dist-info/RECORD
