Metadata-Version: 2.4
Name: quearcode
Version: 0.4.2
Summary: A tool for creating QR Codes
Home-page: https://codeberg.org/gwync/quearcode
Author: Gwyn Ciesla
Author-email: gwync@protonmail.com
License: GPL-3.0-or-later
Classifier: Programming Language :: Python :: 3
Classifier: Operating System :: OS Independent
License-File: COPYING
Requires-Dist: PyGObject
Requires-Dist: qrcode
Requires-Dist: pillow
Dynamic: license-file
